[
  {
    "type": "VarStart",
    "lexeme": "{{",
    "span": {
      "start": {
        "offset": 0,
        "line": 1,
        "column": 1
      },
      "end": {
        "offset": 2,
        "line": 1,
        "column": 3
      }
    }
  },
  {
    "type": "Whitespace",
    "lexeme": " ",
    "span": {
      "start": {
        "offset": 2,
        "line": 1,
        "column": 3
      },
      "end": {
        "offset": 3,
        "line": 1,
        "column": 4
      }
    }
  },
  {
    "type": "Identifier",
    "lexeme": "value",
    "span": {
      "start": {
        "offset": 3,
        "line": 1,
        "column": 4
      },
      "end": {
        "offset": 8,
        "line": 1,
        "column": 9
      }
    }
  },
  {
    "type": "Operator",
    "lexeme": "|",
    "span": {
      "start": {
        "offset": 8,
        "line": 1,
        "column": 9
      },
      "end": {
        "offset": 9,
        "line": 1,
        "column": 10
      }
    }
  },
  {
    "type": "Identifier",
    "lexeme": "replace",
    "span": {
      "start": {
        "offset": 9,
        "line": 1,
        "column": 10
      },
      "end": {
        "offset": 16,
        "line": 1,
        "column": 17
      }
    }
  },
  {
    "type": "Whitespace",
    "lexeme": " ",
    "span": {
      "start": {
        "offset": 16,
        "line": 1,
        "column": 17
      },
      "end": {
        "offset": 17,
        "line": 1,
        "column": 18
      }
    }
  },
  {
    "type": "String",
    "lexeme": "\" \"",
    "span": {
      "start": {
        "offset": 17,
        "line": 1,
        "column": 18
      },
      "end": {
        "offset": 20,
        "line": 1,
        "column": 21
      }
    }
  },
  {
    "type": "Punct",
    "lexeme": ",",
    "span": {
      "start": {
        "offset": 20,
        "line": 1,
        "column": 21
      },
      "end": {
        "offset": 21,
        "line": 1,
        "column": 22
      }
    }
  },
  {
    "type": "Whitespace",
    "lexeme": " ",
    "span": {
      "start": {
        "offset": 21,
        "line": 1,
        "column": 22
      },
      "end": {
        "offset": 22,
        "line": 1,
        "column": 23
      }
    }
  },
  {
    "type": "String",
    "lexeme": "\"-\"",
    "span": {
      "start": {
        "offset": 22,
        "line": 1,
        "column": 23
      },
      "end": {
        "offset": 25,
        "line": 1,
        "column": 26
      }
    }
  },
  {
    "type": "Punct",
    "lexeme": ",",
    "span": {
      "start": {
        "offset": 25,
        "line": 1,
        "column": 26
      },
      "end": {
        "offset": 26,
        "line": 1,
        "column": 27
      }
    }
  },
  {
    "type": "Whitespace",
    "lexeme": " ",
    "span": {
      "start": {
        "offset": 26,
        "line": 1,
        "column": 27
      },
      "end": {
        "offset": 27,
        "line": 1,
        "column": 28
      }
    }
  },
  {
    "type": "Identifier",
    "lexeme": "count",
    "span": {
      "start": {
        "offset": 27,
        "line": 1,
        "column": 28
      },
      "end": {
        "offset": 32,
        "line": 1,
        "column": 33
      }
    }
  },
  {
    "type": "Operator",
    "lexeme": "=",
    "span": {
      "start": {
        "offset": 32,
        "line": 1,
        "column": 33
      },
      "end": {
        "offset": 33,
        "line": 1,
        "column": 34
      }
    }
  },
  {
    "type": "Number",
    "lexeme": "1",
    "span": {
      "start": {
        "offset": 33,
        "line": 1,
        "column": 34
      },
      "end": {
        "offset": 34,
        "line": 1,
        "column": 35
      }
    }
  },
  {
    "type": "Whitespace",
    "lexeme": " ",
    "span": {
      "start": {
        "offset": 34,
        "line": 1,
        "column": 35
      },
      "end": {
        "offset": 35,
        "line": 1,
        "column": 36
      }
    }
  },
  {
    "type": "VarEnd",
    "lexeme": "}}",
    "span": {
      "start": {
        "offset": 35,
        "line": 1,
        "column": 36
      },
      "end": {
        "offset": 37,
        "line": 1,
        "column": 38
      }
    }
  },
  {
    "type": "Text",
    "lexeme": "\n",
    "span": {
      "start": {
        "offset": 37,
        "line": 1,
        "column": 38
      },
      "end": {
        "offset": 38,
        "line": 2,
        "column": 1
      }
    }
  },
  {
    "type": "EOF",
    "lexeme": "",
    "span": {
      "start": {
        "offset": 38,
        "line": 2,
        "column": 1
      },
      "end": {
        "offset": 38,
        "line": 2,
        "column": 1
      }
    }
  }
]