[
  {
    "type": "BlockStart",
    "lexeme": "{%",
    "span": {
      "start": {
        "offset": 0,
        "line": 1,
        "column": 1
      },
      "end": {
        "offset": 2,
        "line": 1,
        "column": 3
      }
    }
  },
  {
    "type": "Whitespace",
    "lexeme": " ",
    "span": {
      "start": {
        "offset": 2,
        "line": 1,
        "column": 3
      },
      "end": {
        "offset": 3,
        "line": 1,
        "column": 4
      }
    }
  },
  {
    "type": "Identifier",
    "lexeme": "set",
    "span": {
      "start": {
        "offset": 3,
        "line": 1,
        "column": 4
      },
      "end": {
        "offset": 6,
        "line": 1,
        "column": 7
      }
    }
  },
  {
    "type": "Whitespace",
    "lexeme": " ",
    "span": {
      "start": {
        "offset": 6,
        "line": 1,
        "column": 7
      },
      "end": {
        "offset": 7,
        "line": 1,
        "column": 8
      }
    }
  },
  {
    "type": "Identifier",
    "lexeme": "greeting",
    "span": {
      "start": {
        "offset": 7,
        "line": 1,
        "column": 8
      },
      "end": {
        "offset": 15,
        "line": 1,
        "column": 16
      }
    }
  },
  {
    "type": "Whitespace",
    "lexeme": " ",
    "span": {
      "start": {
        "offset": 15,
        "line": 1,
        "column": 16
      },
      "end": {
        "offset": 16,
        "line": 1,
        "column": 17
      }
    }
  },
  {
    "type": "BlockEnd",
    "lexeme": "%}",
    "span": {
      "start": {
        "offset": 16,
        "line": 1,
        "column": 17
      },
      "end": {
        "offset": 18,
        "line": 1,
        "column": 19
      }
    }
  },
  {
    "type": "Text",
    "lexeme": "\nHello ",
    "span": {
      "start": {
        "offset": 18,
        "line": 1,
        "column": 19
      },
      "end": {
        "offset": 25,
        "line": 2,
        "column": 7
      }
    }
  },
  {
    "type": "VarStart",
    "lexeme": "{{",
    "span": {
      "start": {
        "offset": 25,
        "line": 2,
        "column": 7
      },
      "end": {
        "offset": 27,
        "line": 2,
        "column": 9
      }
    }
  },
  {
    "type": "Whitespace",
    "lexeme": " ",
    "span": {
      "start": {
        "offset": 27,
        "line": 2,
        "column": 9
      },
      "end": {
        "offset": 28,
        "line": 2,
        "column": 10
      }
    }
  },
  {
    "type": "Identifier",
    "lexeme": "name",
    "span": {
      "start": {
        "offset": 28,
        "line": 2,
        "column": 10
      },
      "end": {
        "offset": 32,
        "line": 2,
        "column": 14
      }
    }
  },
  {
    "type": "Whitespace",
    "lexeme": " ",
    "span": {
      "start": {
        "offset": 32,
        "line": 2,
        "column": 14
      },
      "end": {
        "offset": 33,
        "line": 2,
        "column": 15
      }
    }
  },
  {
    "type": "VarEnd",
    "lexeme": "}}",
    "span": {
      "start": {
        "offset": 33,
        "line": 2,
        "column": 15
      },
      "end": {
        "offset": 35,
        "line": 2,
        "column": 17
      }
    }
  },
  {
    "type": "Text",
    "lexeme": "\n",
    "span": {
      "start": {
        "offset": 35,
        "line": 2,
        "column": 17
      },
      "end": {
        "offset": 36,
        "line": 3,
        "column": 1
      }
    }
  },
  {
    "type": "BlockStart",
    "lexeme": "{%",
    "span": {
      "start": {
        "offset": 36,
        "line": 3,
        "column": 1
      },
      "end": {
        "offset": 38,
        "line": 3,
        "column": 3
      }
    }
  },
  {
    "type": "Whitespace",
    "lexeme": " ",
    "span": {
      "start": {
        "offset": 38,
        "line": 3,
        "column": 3
      },
      "end": {
        "offset": 39,
        "line": 3,
        "column": 4
      }
    }
  },
  {
    "type": "Identifier",
    "lexeme": "endset",
    "span": {
      "start": {
        "offset": 39,
        "line": 3,
        "column": 4
      },
      "end": {
        "offset": 45,
        "line": 3,
        "column": 10
      }
    }
  },
  {
    "type": "Whitespace",
    "lexeme": " ",
    "span": {
      "start": {
        "offset": 45,
        "line": 3,
        "column": 10
      },
      "end": {
        "offset": 46,
        "line": 3,
        "column": 11
      }
    }
  },
  {
    "type": "BlockEnd",
    "lexeme": "%}",
    "span": {
      "start": {
        "offset": 46,
        "line": 3,
        "column": 11
      },
      "end": {
        "offset": 48,
        "line": 3,
        "column": 13
      }
    }
  },
  {
    "type": "Text",
    "lexeme": "\n",
    "span": {
      "start": {
        "offset": 48,
        "line": 3,
        "column": 13
      },
      "end": {
        "offset": 49,
        "line": 4,
        "column": 1
      }
    }
  },
  {
    "type": "EOF",
    "lexeme": "",
    "span": {
      "start": {
        "offset": 49,
        "line": 4,
        "column": 1
      },
      "end": {
        "offset": 49,
        "line": 4,
        "column": 1
      }
    }
  }
]